hls2dash/__init__.py
hls2dash/__main__.py
hls2dash/debug.py
hls2dash/lib/MPD.py
hls2dash/lib/MPDAdaptationSet.py
hls2dash/lib/MPDRepresentation.py
hls2dash/lib/TS.py
hls2dash/lib/TSRemux.py
hls2dash/lib/__init__.py
hls2dash/lib/util.py
hls2dash/tsremux/__init__.py
hls2dash/tsremux/__main__.py
hls2dash-0.2.1.dist-info/DESCRIPTION.rst
hls2dash-0.2.1.dist-info/METADATA
hls2dash-0.2.1.dist-info/RECORD
hls2dash-0.2.1.dist-info/WHEEL
hls2dash-0.2.1.dist-info/entry_points.txt
hls2dash-0.2.1.dist-info/metadata.json
hls2dash-0.2.1.dist-info/top_level.txt
