Metadata-Version: 2.0
Name: hls2dash
Version: 0.2.1
Summary: Command line tools for HLS to MPEG DASH repackaging
Home-page: https://github.com/Eyevinn/hls-to-dash
Author: Jonas Birme
Author-email: jonas.birme@eyevinn.se
License: MIT
Platform: UNKNOWN
Requires-Dist: ffprobe (>=0.5)
Requires-Dist: m3u8 (>=0.2.10)
Requires-Dist: pycurl
